yabai_client/__init__.py
yabai_client-0.0.3.dist-info/LICENSE.txt
yabai_client-0.0.3.dist-info/METADATA
yabai_client-0.0.3.dist-info/WHEEL
yabai_client-0.0.3.dist-info/top_level.txt
yabai_client-0.0.3.dist-info/RECORD
