Metadata-Version: 2.1
Name: yabai-client
Version: 0.0.3
Summary: Python reimplementation of the yabai client.
Home-page: UNKNOWN
Author: Alcasa
Author-email: alcasa@arsbrevis.de
License: LICENSE.txt
Platform: UNKNOWN
License-File: LICENSE.txt
